Workbook
Name CASE: 'LBO - YM Final'!$E$7
Name CASE: #REF!
Name CIRC: 'LBO - YM Final'!$E$6
Name CIRC: #REF!
Name PIK: 'LBO - YM Final'!$E$8:$E$8
Name PIK: #REF!

Sheet Cover
B2: Cover
A4: x | B4: Creating the Burger King LBO Model Processes
B5: - Assumptions Provided | G5: - Forecasting Cash Flow Statement
B6: - Sources and Uses Table | G6: - Forecasting Balance Sheet
B7: - Building the Operating Model | G7: - USD & EUR Debt Tranches (e.g. revolver)
B8: - Building the Debt Schedule | G8: - Mandatory Debt Repayments
B9: - IRR Calculations | G9: - PIK
B10: - Obtain Assumptions Based on Real Tax Figures | G10: - Cash Sweep
B11: - Sources and Uses Table | G11: - LIBOR
B12: - Operating Model With Two Scenarios | G12: - Amortization of Financing Fees
B13: - Debt Schedule With Circuit Breaker | G13: - Sensitivity Table
B14: - Revenue Cases | G14: - Adding a DCF

Sheet LBO - YM Final
B2: LBO
A4: x | B4: Switches
B6: Circuit Breaker | E6: OFF | I6: IRR (for reference) | K6: =K308 -> 0.2124125
B7: Case | E7: 2 | F7: =IF(E7=1,"Conservative","Management") -> Management | I7: Revolver Check | K7: =G218 -> OK
B8: PIK Toggle | E8: 1 | F8: =IF(E8=1,"Cash","PIK") -> Cash
A10: x | B10: Assumptions
B12: Transaction Background | H12: Valuation at Entry
B13: Company name | E13: Burger King | H13: Offer value / share | K13: 24
B14: Ticker | E14: BKC | H14: % Premium / Discount | K14: =K13/E15-1 -> 0.27253446
B15: Latest closing share price | E15: 18.86
B16: Latest closing share price date | E16: 40422 | H16: Offer value (Equity value) | K16: =K13*K17 -> 3325.4354
H17: Diluted Shares Outstanding | K17: ='Shares - YM'!E16 -> 138.55981
B19: Transaction Financials and Assumptions | H19: Debt | K19: =E21 -> 755.4
B20: LTM EBITDA | E20: =F100 -> 444.6 | H20: Cash | K20: =E22 -> 187.6
B21: Debt | E21: =93.3+667.7-5.6 -> 755.4
B22: Cash | E22: =187.6 -> 187.6 | H22: Enterprise Value | K22: =K16+K19-K20 -> 3893.2354
B23: Minimum Cash | E23: =E22-69.4 -> 118.2 | H23: LTM EBITDA | K23: =E20 -> 444.6
B24: Exit Multiple | E24: =K24 -> 8.7567148 | H24: Entry Multiple | K24: =K22/K23 -> 8.7567148
B26: Capital Structure
E27: Amount | F27: xEBITDA | G27: Interest (%) | H27: Fees (%) | I27: Fee ($) | J27: Term | K27: Amortization
B28: Revolver | E28: 0 | F28: =E28/E$20 -> 0 | G28: 0.045 | H28: 0 | I28: =E28*H28 -> 0 | J28: 5 | K28: =I28/J28 -> 0
B29: Secured Term Loan - USD Tranche | E29: 1510 | F29: =E29/E$20 -> 3.3963113 | G29: 0.0682 | H29: 0.027 | I29: =E29*H29 -> 40.77 | J29: 6 | K29: =I29/J29 -> 6.795
B30: Secured Term Loan - EUR Tranche | E30: 334.2 | F30: =E30/E$20 -> 0.75168691 | G30: 0.0711 | H30: 0.0251 | I30: =E30*H30 -> 8.38842 | J30: 6 | K30: =I30/J30 -> 1.39807
B31: Senior Notes | E31: 800 | F31: =E31/E$20 -> 1.7993702 | G31: 0.1019 | H31: 0.0251 | I31: =E31*H31 -> 20.08 | J31: 8 | K31: =I31/J31 -> 2.51 | L31: PIK
B32: Subordinated Notes | E32: 0 | F32: =E32/E$20 -> 0 | G32: 0.1 | H32: 0 | I32: =E32*H32 -> 0 | J32: 5 | K32: =I32/J32 -> 0 | L32: 0.05
B33: Preferred Equity | E33: 0 | F33: =E33/E$20 -> 0 | G33: 0.1 | H33: 0 | I33: =E33*H33 -> 0 | J33: 5 | K33: =I33/J33 -> 0
B35: Total | E35: =SUM(E28:E33) -> 2644.2 | F35: =SUM(F28:F33) -> 5.9473684 | I35: =SUM(I28:I33) -> 69.23842 | K35: =SUM(K28:K33) -> 10.70307
A37: x | B37: Sources and Uses
B39: Sources | H39: Uses
D40: Amount | E40: xEBITDA | F40: % Capital | I40: Amount | J40: xEBITDA | K40: % Capital
B41: =B28 -> Revolver | D41: =E28 -> 0 | E41: =D41/$E$20 -> 0 | F41: =D41/$D$50 -> 0 | H41: Equity Payment | I41: =K16 -> 3325.4354 | J41: =I41/$E$20 -> 7.4796118 | K41: =I41/$D$50 -> 0.77813446
B42: =B29 -> Secured Term Loan - USD Tranche | D42: =E29 -> 1510 | E42: =D42/$E$20 -> 3.3963113 | F42: =D42/$D$50 -> 0.35333209 | H42: Debt Refinanciang | I42: =E21 -> 755.4 | J42: =I42/$E$20 -> 1.6990553 | K42: =I42/$D$50 -> 0.17675964
B43: =B30 -> Secured Term Loan - EUR Tranche | D43: =E30 -> 334.2 | E43: =D43/$E$20 -> 0.75168691 | F43: =D43/$D$50 -> 0.078201048 | H43: Transaction Fees | I43: 91.2 | J43: =I43/$E$20 -> 0.20512821 | K43: =I43/$D$50 -> 0.021340322
B44: =B31 -> Senior Notes | D44: =E31 -> 800 | E44: =D44/$E$20 -> 1.7993702 | F44: =D44/$D$50 -> 0.18719581 | H44: Financiang Fees | I44: =I35 -> 69.23842 | J44: =I44/$E$20 -> 0.15573194 | K44: =I44/$D$50 -> 0.016201427
B45: =B32 -> Subordinated Notes | D45: 0 | E45: =D45/$E$20 -> 0 | F45: =D45/$D$50 -> 0
B46: =B33 -> Preferred Equity | D46: 0 | E46: =D46/$E$20 -> 0 | F46: =D46/$D$50 -> 0 | H46: Other | I46: 32.326172 | J46: =I46/$E$20 -> 0.072708439 | K46: =I46/$D$50 -> 0.0075641548
B47: Cash on hand | D47: =E22-E23 -> 69.4 | E47: =D47/$E$20 -> 0.15609537 | F47: =D47/$D$50 -> 0.016239236
B48: Sponsor Equity | D48: =D50-SUM(D41:D47) -> 1560 | E48: =D48/$E$20 -> 3.5087719 | F48: =D48/$D$50 -> 0.36503182
B50: Total | D50: =I50 -> 4273.6 | E50: =SUM(E41:E48) -> 9.6122357 | F50: =SUM(F42:F48) -> 1 | H50: Total | I50: =SUM(I41:I47) -> 4273.6 | J50: =SUM(J41:J47) -> 9.6122357 | K50: =SUM(K41:K47) -> 1
A52: x | B52: Financials (6/30 FYE)
B54: Assumptions | D54: 2008 | E54: =D54+1 -> 2009 | F54: =E54+1 -> 2010 | G54: =F54+1 -> 2011 | H54: =G54+1 -> 2012 | I54: =H54+1 -> 2013 | J54: =I54+1 -> 2014 | K54: =J54+1 -> 2015 | M54: Step
B56: Revenue Growth | D56: -- | E56: =E63/D63-1 -> 0.033690471 | F56: =F63/E63-1 -> -0.013872468 | G56: =G63/F63-1 -> 0.028694749 | H56: =H63/G63-1 -> -0.18337218 | I56: =I63/H63-1 -> -0.10371075 | J56: =J63/I63-1 -> 0.013800425 | K56: =K63/J63-1 -> 0.059685864 | M56: 0
B57: Gross Margin | D57: =D69/D63 -> 0.37344686 | E57: =E69/E63 -> 0.35221092 | F57: =F69/F63 -> 0.35464791 | G57: =F57 -> 0.35464791 | H57: =G57+$M$57 -> 0.37214791 | I57: =H57+$M$57 -> 0.38964791 | J57: =I57+$M$57 -> 0.40714791 | K57: =J57+$M$57 -> 0.42464791 | M57: 0.0175
B58: OpEx Margin | D58: =D72/D63 -> 0.22915224 | E58: =E72/E63 -> 0.21845196 | F58: =F72/F63 -> 0.22160499 | G58: =F58 -> 0.22160499 | H58: =G58-$M$58 -> 0.19960499 | I58: =H58-$M$58 -> 0.17760499 | J58: =I58-$M$58 -> 0.15560499 | K58: =J58-$M$58 -> 0.13360499 | M58: 0.022
B59: Tax Rate | D59: =D90/D87 -> 0.35290102 | E59: =E90/E87 -> 0.29740169 | F59: =F90/F87 -> 0.34294759 | G59: =F59-$M$59 -> 0.33794759 | H59: =G59-$M$59 -> 0.33294759 | I59: =H59-$M$59 -> 0.32794759 | J59: =I59-$M$59 -> 0.32294759 | K59: =J59-$M$59 -> 0.31794759 | M59: 0.005
A61: x | B61: Operating Model | D61: 2008 | E61: =D61+1 -> 2009 | F61: =E61+1 -> 2010 | G61: =F61+1 -> 2011 | H61: =G61+1 -> 2012 | I61: =H61+1 -> 2013 | J61: =I61+1 -> 2014 | K61: =J61+1 -> 2015
B63: Revenue | D63: 2454.7 | E63: 2537.4 | F63: 2502.2 | G63: 2574 | H63: 2102 | I63: 1884 | J63: 1910 | K63: 2024
B64: % growth | D64: -- | E64: =E63/D$63-1 -> 0.033690471 | F64: =F63/E$63-1 -> -0.013872468 | G64: =G63/F$63-1 -> 0.028694749 | H64: =H63/G$63-1 -> -0.18337218 | I64: =I63/H$63-1 -> -0.10371075 | J64: =J63/I$63-1 -> 0.013800425 | K64: =K63/J$63-1 -> 0.059685864
B66: COGS | D66: 1538 | E66: 1643.7 | F66: 1614.8 | G66: =IF(CASE=2,"--",G63-G69) -> -- | H66: =IF(CASE=2,"--",H63-H69) -> -- | I66: =IF(CASE=2,"--",I63-I69) -> -- | J66: =IF(CASE=2,"--",J63-J69) -> -- | K66: =IF(CASE=2,"--",K63-K69) -> --
B67: % of sales | D67: =D66/D$63 -> 0.62655314 | E67: =E66/E$63 -> 0.64778908 | F67: =F66/F$63 -> 0.64535209 | G67: =IF(CASE=2,"--",G66/G$63) -> -- | H67: =IF(CASE=2,"--",H66/H$63) -> -- | I67: =IF(CASE=2,"--",I66/I$63) -> -- | J67: =IF(CASE=2,"--",J66/J$63) -> -- | K67: =IF(CASE=2,"--",K66/K$63) -> --
B69: Gross Profit | D69: =D63-D66 -> 916.7 | E69: =E63-E66 -> 893.7 | F69: =F63-F66 -> 887.4 | G69: =IF(CASE=2,"--",G70*G63) -> -- | H69: =IF(CASE=2,"--",H70*H63) -> -- | I69: =IF(CASE=2,"--",I70*I63) -> -- | J69: =IF(CASE=2,"--",J70*J63) -> -- | K69: =IF(CASE=2,"--",K70*K63) -> --
B70: % of sales | D70: =D57 -> 0.37344686 | E70: =E57 -> 0.35221092 | F70: =F57 -> 0.35464791 | G70: =IF(CASE=2,"--",G57) -> -- | H70: =IF(CASE=2,"--",H57) -> -- | I70: =IF(CASE=2,"--",I57) -> -- | J70: =IF(CASE=2,"--",J57) -> -- | K70: =IF(CASE=2,"--",K57) -> --
B72: OpEx | D72: 562.5 | E72: 554.3 | F72: 554.5 | G72: =IF(CASE=2,"--",G73*G63) -> -- | H72: =IF(CASE=2,"--",H73*H63) -> -- | I72: =IF(CASE=2,"--",I73*I63) -> -- | J72: =IF(CASE=2,"--",J73*J63) -> -- | K72: =IF(CASE=2,"--",K73*K63) -> --
B73: % of sales | D73: =D72/D$63 -> 0.22915224 | E73: =E72/E$63 -> 0.21845196 | F73: =F72/F$63 -> 0.22160499 | G73: =IF(CASE=2,"--",G58) -> -- | H73: =IF(CASE=2,"--",H58) -> -- | I73: =IF(CASE=2,"--",I58) -> -- | J73: =IF(CASE=2,"--",J58) -> -- | K73: =IF(CASE=2,"--",K58) -> --
B75: EBIT | D75: =D69-D72 -> 354.2 | E75: =E69-E72 -> 339.4 | F75: =F69-F72 -> 332.9 | G75: =CHOOSE(CASE,G78,G81) -> 351 | H75: =CHOOSE(CASE,H78,H81) -> 426 | I75: =CHOOSE(CASE,I78,I81) -> 465 | J75: =CHOOSE(CASE,J78,J81) -> 528 | K75: =CHOOSE(CASE,K78,K81) -> 589
B76: % of sales | D76: =D75/D63 -> 0.14429462 | E76: =E75/E63 -> 0.13375897 | F76: =F75/F63 -> 0.13304292 | G76: =G75/G63 -> 0.13636364 | H76: =H75/H63 -> 0.20266413 | I76: =I75/I63 -> 0.24681529 | J76: =J75/J63 -> 0.27643979 | K76: =K75/K63 -> 0.29100791
B78: EBIT - Conservative | G78: =IF(CASE=1,G69-G72,G78) -> 342.45248 | H78: =IF(CASE=1,H69-H72,H78) -> 362.68522 | I78: =IF(CASE=1,I69-I72,I78) -> 399.48887 | J78: =IF(CASE=1,J69-J72,J78) -> 480.44698 | K78: =IF(CASE=1,K69-K72,K78) -> 589.07087
B79: % of sales | G79: =G78/G$63 -> 0.13304292 | H79: =H78/H$63 -> 0.17254292 | I79: =I78/I$63 -> 0.21204292 | J79: =J78/J$63 -> 0.25154292 | K79: =K78/K$63 -> 0.29104292
B81: EBIT - Management | G81: 351 | H81: 426 | I81: 465 | J81: 528 | K81: 589
B82: % of sales | G82: =G81/G$63 -> 0.13636364 | H82: =H81/H$63 -> 0.20266413 | I82: =I81/I$63 -> 0.24681529 | J82: =J81/J$63 -> 0.27643979 | K82: =K81/K$63 -> 0.29100791
B84: Interest Expense | D84: 67.1 | E84: 57.3 | F84: 49.6 | G84: =G294 -> 207.49034 | H84: =H294 -> 204.80293 | I84: =I294 -> 198.70181 | J84: =J294 -> 188.40722 | K84: =K294 -> 174.33103
B85: Interest Income | D85: 5.9 | E85: 2.7 | F85: 1 | G85: =G273 -> 0.63006397 | H85: =H273 -> 0.63006397 | I85: =I273 -> 0.63006397 | J85: =J273 -> 0.63006397 | K85: =K273 -> 0.63006389
B87: EBT | D87: =D75-D84+D85 -> 293 | E87: =E75-E84+E85 -> 284.8 | F87: =F75-F84+F85 -> 284.3 | G87: =G75-G84+G85 -> 144.13972 | H87: =H75-H84+H85 -> 221.82713 | I87: =I75-I84+I85 -> 266.92825 | J87: =J75-J84+J85 -> 340.22284 | K87: =K75-K84+K85 -> 415.29903
B88: % of sales | D88: =D87/D$63 -> 0.11936285 | E88: =E87/E$63 -> 0.11224088 | F88: =F87/F$63 -> 0.11362001 | G88: =G87/G$63 -> 0.055998339 | H88: =H87/H$63 -> 0.10553146 | I88: =I87/I$63 -> 0.14168166 | J88: =J87/J$63 -> 0.17812714 | K88: =K87/K$63 -> 0.20518727
B90: Taxes | D90: 103.4 | E90: 84.7 | F90: 97.5 | G90: =G87*G91 -> 48.711672 | H90: =H87*H91 -> 73.856808 | I90: =I87*I91 -> 87.538478 | J90: =J87*J91 -> 109.87415 | K90: =K87*K91 -> 132.04333
B91: % tax rate | D91: =D59 -> 0.35290102 | E91: =E59 -> 0.29740169 | F91: =F59 -> 0.34294759 | G91: =G59 -> 0.33794759 | H91: =H59 -> 0.33294759 | I91: =I59 -> 0.32794759 | J91: =J59 -> 0.32294759 | K91: =K59 -> 0.31794759
B93: Net Income | D93: =D87-D90 -> 189.6 | E93: =E87-E90 -> 200.1 | F93: =F87-F90 -> 186.8 | G93: =G87-G90 -> 95.428051 | H93: =H87-H90 -> 147.97032 | I93: =I87-I90 -> 179.38978 | J93: =J87-J90 -> 230.3487 | K93: =K87-K90 -> 283.2557
B94: % of sales | D94: =D93/D$63 -> 0.077239581 | E94: =E93/E$63 -> 0.078860251 | F94: =F93/F$63 -> 0.074654304 | G94: =G93/G$63 -> 0.037073835 | H94: =H93/H$63 -> 0.070395015 | I94: =I93/I$63 -> 0.095217503 | J94: =J93/J$63 -> 0.12060141 | K94: =K93/K$63 -> 0.13994847
B96: EBITDA Reconciliation
B97: EBIT | D97: =D75 -> 354.2 | E97: =E75 -> 339.4 | F97: =F75 -> 332.9
B98: D&A | D98: 95.6 | E98: 98.1 | F98: 111.7
B99: Adjustments | D99: 0 | E99: =1.5+2 -> 3.5 | F99: 0
B100: EBITDA | D100: =SUM(D97:D99) -> 449.8 | E100: =SUM(E97:E99) -> 441 | F100: =SUM(F97:F99) -> 444.6
B101: % of sales | D101: =D100/D$63 -> 0.18324031 | E101: =E100/E$63 -> 0.17379995 | F101: =F100/F$63 -> 0.17768364
B103: EBITDA | D103: =D100 -> 449.8 | E103: =E100 -> 441 | F103: =F100 -> 444.6 | G103: =CHOOSE(CASE,G106,G109) -> 464 | H103: =CHOOSE(CASE,H106,H109) -> 518 | I103: =CHOOSE(CASE,I106,I109) -> 563 | J103: =CHOOSE(CASE,J106,J109) -> 620 | K103: =CHOOSE(CASE,K106,K109) -> 685
B104: % of sales | D104: =D101 -> 0.18324031 | E104: =E101 -> 0.17379995 | F104: =F101 -> 0.17768364 | G104: =G103/G$63 -> 0.18026418 | H104: =H103/H$63 -> 0.24643197 | I104: =I103/I$63 -> 0.29883227 | J104: =J103/J$63 -> 0.32460733 | K104: =K103/K$63 -> 0.33843874
B106: EBITDA - Conservative | G106: =G163+G78 -> 450.7656 | H106: =H163+H78 -> 452.66874 | I106: =I163+I78 -> 481.05278 | J106: =J163+J78 -> 562.81507 | K106: =K163+K78 -> 675.44187
B107: % of sales | G107: =G106/G$63 -> 0.17512261 | H107: =H106/H$63 -> 0.21535145 | I107: =I106/I$63 -> 0.25533587 | J107: =J106/J$63 -> 0.29466757 | K107: =K106/K$63 -> 0.33371634
B109: EBITDA - Management | G109: 464 | H109: 518 | I109: 563 | J109: 620 | K109: 685
B110: % of sales | G110: =G109/G$63 -> 0.18026418 | H110: =H109/H$63 -> 0.24643197 | I110: =I109/I$63 -> 0.29883227 | J110: =J109/J$63 -> 0.32460733 | K110: =K109/K$63 -> 0.33843874
A112: x | B112: Working Capital | D112: 2008 | E112: =D112+1 -> 2009 | F112: =E112+1 -> 2010 | G112: =F112+1 -> 2011 | H112: =G112+1 -> 2012 | I112: =H112+1 -> 2013 | J112: =I112+1 -> 2014 | K112: =J112+1 -> 2015
B114: Accounts Receivable | D114: 139.3 | E114: 130 | F114: 142.9 | G114: =G115*G$63 -> 141.64857 | H114: =H115*H$63 -> 115.67416 | I114: =I115*I$63 -> 103.6775 | J114: =J115*J$63 -> 105.1083 | K114: =K115*K$63 -> 111.38178
B115: % of sales | D115: =D114/D$63 -> 0.056748279 | E115: =E114/E$63 -> 0.051233546 | F115: =F114/F$63 -> 0.057109743 | G115: =AVERAGE(D115:F115) -> 0.055030523 | H115: =G115 -> 0.055030523 | I115: =H115 -> 0.055030523 | J115: =I115 -> 0.055030523 | K115: =J115 -> 0.055030523
B117: Prepaids and Other Current Assets | D117: =53.5+45.2 -> 98.7 | E117: =86.4+32.5 -> 118.9 | F117: =88.4+15.1 -> 103.5 | G117: =G118*G$63 -> 110.19394 | H117: =H118*H$63 -> 89.987439 | I117: =I118*I$63 -> 80.654774 | J117: =J118*J$63 -> 81.767844 | K117: =K118*K$63 -> 86.648229
B118: % of sales | D118: =D117/D$63 -> 0.040208579 | E118: =E117/E$63 -> 0.04685899 | F118: =F117/F$63 -> 0.0413636 | G118: =AVERAGE(D118:F118) -> 0.04281039 | H118: =G118 -> 0.04281039 | I118: =H118 -> 0.04281039 | J118: =I118 -> 0.04281039 | K118: =J118 -> 0.04281039
B120: Accounts Payable | D120: 129.5 | E120: 127 | F120: 106.9 | G120: =G121*G$63 -> 109.96747 | H120: =H121*H$63 -> 89.802494 | I120: =I121*I$63 -> 80.48901 | J120: =J121*J$63 -> 81.599792 | K120: =K121*K$63 -> 86.470146
B121: % of sales | D121: =D120/D$63 -> 0.052755938 | E121: =E120/E$63 -> 0.050051234 | F121: =F120/F$63 -> 0.042722404 | G121: =F121 -> 0.042722404 | H121: =G121 -> 0.042722404 | I121: =H121 -> 0.042722404 | J121: =I121 -> 0.042722404 | K121: =J121 -> 0.042722404
M122: Note
B123: Accrued Advertising | D123: 77.2 | E123: 67.8 | F123: 71.9 | G123: =G124*G$63 -> 74.564361 | H123: =H124*H$63 -> 60.891332 | I123: =I124*I$63 -> 54.576246 | J123: =J124*J$63 -> 55.329421 | K123: =K124*K$63 -> 58.631805 | M123: Negative on cfs for assets = outflow of cash
B124: % of sales | D124: =D123/D$63 -> 0.031449872 | E124: =E123/E$63 -> 0.026720265 | F124: =F123/F$63 -> 0.028734713 | G124: =AVERAGE(D124:F124) -> 0.028968283 | H124: =G124 -> 0.028968283 | I124: =H124 -> 0.028968283 | J124: =I124 -> 0.028968283 | K124: =J124 -> 0.028968283 | M124: Positive on cfs for assets = inflow of cash
M125: Negative on cfs for liabilities = inflow of cash
B126: Other Accrued Liabilities | D126: 241.9 | E126: 220 | F126: 200.9 | G126: =G127*G$63 -> 206.66477 | H126: =H127*H$63 -> 168.7682 | I126: =I127*I$63 -> 151.26513 | J126: =J127*J$63 -> 153.35265 | K126: =K127*K$63 -> 162.50564 | M126: Positive on cfs for liabilities = outflow of cash
B127: % of sales | D127: =D126/D$63 -> 0.098545647 | E127: =E126/E$63 -> 0.086702924 | F127: =F126/F$63 -> 0.080289345 | G127: =F127 -> 0.080289345 | H127: =G127 -> 0.080289345 | I127: =H127 -> 0.080289345 | J127: =I127 -> 0.080289345 | K127: =J127 -> 0.080289345
B129: Net Working Capital | D129: =SUM(D114,D117)-SUM(D120,D123,D126) -> -210.6 | E129: =SUM(E114,E117)-SUM(E120,E123,E126) -> -165.9 | F129: =SUM(F114,F117)-SUM(F120,F123,F126) -> -133.3 | G129: =SUM(G114,G117)-SUM(G120,G123,G126) -> -139.3541 | H129: =SUM(H114,H117)-SUM(H120,H123,H126) -> -113.80043 | I129: =SUM(I114,I117)-SUM(I120,I123,I126) -> -101.9981 | J129: =SUM(J114,J117)-SUM(J120,J123,J126) -> -103.40572 | K129: =SUM(K114,K117)-SUM(K120,K123,K126) -> -109.57758
B130: % of sales | D130: =D129/D$63 -> -0.085794598 | E130: =E129/E$63 -> -0.065381887 | F130: =F129/F$63 -> -0.05327312 | G130: =AVERAGE(D130:F130) -> -0.068149868 | H130: =H129/H$63 -> -0.054139121 | I130: =I129/I$63 -> -0.054139121 | J130: =J129/J$63 -> -0.054139121 | K130: =K129/K$63 -> -0.054139121
B132: Change in Net Working Capital | D132: -- | E132: =E129-D129 -> 44.7 | F132: =F129-E129 -> 32.6 | G132: =G129-F129 -> -6.0540962 | H132: =H129-G129 -> 25.553665 | I132: =I129-H129 -> 11.802328 | J132: =J129-I129 -> -1.4076171 | K132: =K129-J129 -> -6.1718597
B133: % of sales | D133: -- | E133: =E132/E$63 -> 0.017616458 | F133: =F132/F$63 -> 0.013028535 | G133: =G132/G$63 -> -0.0023520187 | H133: =H132/H$63 -> 0.012156834 | I133: =I132/I$63 -> 0.0062645055 | J133: =J132/J$63 -> -0.00073697232 | K133: =K132/K$63 -> -0.0030493378
A135: x | B135: Long Lived Assets | D135: 2008 | E135: =D135+1 -> 2009 | F135: =E135+1 -> 2010 | G135: =F135+1 -> 2011 | H135: =G135+1 -> 2012 | I135: =H135+1 -> 2013 | J135: =I135+1 -> 2014 | K135: =J135+1 -> 2015
B137: CapEx | D137: 178.2 | E137: 204 | F137: 150.3 | G137: =G138*G63 -> 182.80533 | H137: =H138*H63 -> 149.28392 | I137: =I138*I63 -> 133.80157 | J137: =J138*J63 -> 135.64809 | K137: =K138*K63 -> 143.74436
B138: % of sales | D138: =D137/D$63 -> 0.072595429 | E138: =E137/E$63 -> 0.080397257 | F138: =F137/F$63 -> 0.060067141 | G138: =AVERAGE(D138:F138) -> 0.071019942 | H138: =G138 -> 0.071019942 | I138: =H138 -> 0.071019942 | J138: =I138 -> 0.071019942 | K138: =J138 -> 0.071019942
...

Sheet DCF - YM
B2: DCF
B4: WACC | D4: 0.1
B5: TGR | D5: 0.025
F6: 1 | G6: 2 | H6: 3 | I6: 4 | J6: 5 | L6: Year - Discount Period
B7: DCF (6/30, USD M) | E7: 2010A | F7: 2011E | G7: 2012E | H7: 2013E | I7: 2014E | J7: 2015E
B8: Revenue | E8: ='LBO - YM Final'!F63 -> 2502.2 | F8: ='LBO - YM Final'!G63 -> 2574 | G8: ='LBO - YM Final'!H63 -> 2102 | H8: ='LBO - YM Final'!I63 -> 1884 | I8: ='LBO - YM Final'!J63 -> 1910 | J8: ='LBO - YM Final'!K63 -> 2024
B9: % growth | F9: =F8/E8-1 -> 0.028694749 | G9: =G8/F8-1 -> -0.18337218 | H9: =H8/G8-1 -> -0.10371075 | I9: =I8/H8-1 -> 0.013800425 | J9: =J8/I8-1 -> 0.059685864
B11: EBIT | E11: ='LBO - YM Final'!F75 -> 332.9 | F11: ='LBO - YM Final'!G75 -> 351 | G11: ='LBO - YM Final'!H75 -> 426 | H11: ='LBO - YM Final'!I75 -> 465 | I11: ='LBO - YM Final'!J75 -> 528 | J11: ='LBO - YM Final'!K75 -> 589
B12: % of sales | F12: =E11/F8 -> 0.12933178 | G12: =F11/G8 -> 0.16698382 | H12: =G11/H8 -> 0.22611465 | I12: =H11/I8 -> 0.2434555 | J12: =I11/J8 -> 0.26086957
B14: Taxes | E14: =E11*E15 -> 114.16725 | F14: =F11*F15 -> 118.6196 | G14: =G11*G15 -> 141.83567 | H14: =H11*H15 -> 152.49563 | I14: =I11*I15 -> 170.51633 | J14: =J11*J15 -> 187.27113
B15: Tax rate | E15: ='LBO - YM Final'!F91 -> 0.34294759 | F15: ='LBO - YM Final'!G91 -> 0.33794759 | G15: ='LBO - YM Final'!H91 -> 0.33294759 | H15: ='LBO - YM Final'!I91 -> 0.32794759 | I15: ='LBO - YM Final'!J91 -> 0.32294759 | J15: ='LBO - YM Final'!K91 -> 0.31794759
B17: EBIAT | F17: =F11-F14 -> 232.3804 | G17: =G11-G14 -> 284.16433 | H17: =H11-H14 -> 312.50437 | I17: =I11-I14 -> 357.48367 | J17: =J11-J14 -> 401.72887
B19: D&A | F19: ='LBO - YM Final'!G166 -> 113 | G19: ='LBO - YM Final'!H166 -> 92 | H19: ='LBO - YM Final'!I166 -> 98 | I19: ='LBO - YM Final'!J166 -> 92 | J19: ='LBO - YM Final'!K166 -> 96
B20: % of sales | F20: =F19/F8 -> 0.043900544 | G20: =G19/G8 -> 0.04376784 | H20: =H19/H8 -> 0.052016985 | I20: =I19/I8 -> 0.048167539 | J20: =J19/J8 -> 0.04743083
B22: CapEx | F22: ='LBO - YM Final'!G137 -> 182.80533 | G22: ='LBO - YM Final'!H137 -> 149.28392 | H22: ='LBO - YM Final'!I137 -> 133.80157 | I22: ='LBO - YM Final'!J137 -> 135.64809 | J22: ='LBO - YM Final'!K137 -> 143.74436
B23: % of sales | F23: =F22/F8 -> 0.071019942 | G23: =G22/G8 -> 0.071019942 | H23: =H22/H8 -> 0.071019942 | I23: =I22/I8 -> 0.071019942 | J23: =J22/J8 -> 0.071019942
B25: Change in NWC | F25: ='LBO - YM Final'!G132 -> -6.0540962 | G25: ='LBO - YM Final'!H132 -> 25.553665 | H25: ='LBO - YM Final'!I132 -> 11.802328 | I25: ='LBO - YM Final'!J132 -> -1.4076171 | J25: ='LBO - YM Final'!K132 -> -6.1718597
B26: % of sales | F26: =F25/F8 -> -0.0023520187 | G26: =G25/G8 -> 0.012156834 | H26: =H25/H8 -> 0.0062645055 | I26: =I25/I8 -> -0.00073697232 | J26: =J25/J8 -> -0.0030493378
B28: Unlevered FCF | F28: =F17+F19-F22-F25 -> 168.62916 | G28: =G17+G19-G22-G25 -> 201.32674 | H28: =H17+H19-H22-H25 -> 264.90047 | I28: =I17+I19-I22-I25 -> 315.2432 | J28: =J17+J19-J22-J25 -> 360.15637
B29: PV of Unlevered FCF | F29: =F28/(1+$D$4)^F6 -> 153.29924 | G29: =G28/(1+$D$4)^G6 -> 166.38574 | H29: =H28/(1+$D$4)^H6 -> 199.02364 | I29: =I28/(1+$D$4)^I6 -> 215.31535 | J29: =J28/(1+$D$4)^J6 -> 223.62877
B31: Terminal Value | J31: =(J28*(1+D5))/(D4-D5) -> 4922.137
B32: PV of Terminal Value | J32: =J31/(1+D4)^J6 -> 3056.2598
B34: Enterprise Value | J34: =SUM(F29:J29,J32) -> 4013.9125
B35: Cash | J35: ='LBO - YM Final'!E22 -> 187.6
B36: Debt | J36: ='LBO - YM Final'!E21 -> 755.4
B37: Equity Value | J37: =J34+J35-J36 -> 3446.1125
B39: FDSO | J39: ='LBO - YM Final'!K17 -> 138.55981
B40: Share Price | J40: ='DCF - YM'!J37/'DCF - YM'!J39 -> 24.870939
B41: Offer Price (For Reference) | J41: ='LBO - YM Final'!K13 -> 24
B42: Discount / (Premium) | J42: =J41/J40-1 -> -0.03501834

Sheet WACC - YM
B2: WACC
B4: WACC = % of equity x cost of equity + % of debt x cost of debt x (1 - Tax Rate)
B5: Cost of equity = Risk free rate + Beta x Market Risk Premium
A7: x | B7: WACC
B8: Market Cap | F8: ='LBO - YM Final'!E15*'LBO - YM Final'!K17 -> 2613.238
B9: % of Equity
B10: Cost of Equity
B11: Risk Free Rate | F11: 0.0272 | G11: 10Y TREASURY YIELD ON 9/1/2010
B12: Beta | G12: HISTORICAL BETA ON 9/1/2010
B13: Market Risk Premium
B15: Debt
B16: % of Debt
B17: Cost of Debt
B18: Tax Rate
B20: Total
A22: x | B22: WACC

Sheet Shares - YM
B2: Diluted Share Count Calculation
A4: x | B4: Full Diluted Shares
B6: Offer price | E6: ='LBO - YM Final'!K13 -> 24
B7: Basic shares outstanding (latest filing) | E7: 136.55564
B8: In-the-money exercisable options | E8: =E32 -> 7.4212
B9: Total proceeds ($mm) | E9: =SUMPRODUCT(D21:D31,E21:E31) -> 129.35152
B10: Total shares repurchased (mm) | E10: =E9/E6 -> 5.3896465
B11: Net dilutive options | E11: =E8-E10 -> 2.0315535
B12: Dilutive impact of shares from other securities | E12: 1.7296
B14: Settled stock based comp | E14: =48.1/E6 -> 2.0041667
B16: Net diluted shares outstanding | E16: =E7+E14 -> 138.55981
A18: x | B18: Options outstanding
C20: Outstanding | D20: Exercise price | E20: Dilutive Shares
B21: 1 | C21: 7.4212 | D21: 17.43 | E21: =IF(D21<$E$6,C21) -> 7.4212
B22: =B21+1 -> 2 | E22: =IF(D22<$E$6,C22) -> 0
B24: =B22+1 -> 3 | E24: =IF(D24<$E$6,C24) -> 0
B25: =B24+1 -> 4 | E25: =IF(D25<$E$6,C25) -> 0
B26: =B25+1 -> 5 | E26: =IF(D26<$E$6,C26) -> 0
B27: =B26+1 -> 6 | E27: =IF(D27<$E$6,C27) -> 0
B28: =B27+1 -> 7 | E28: =IF(D28<$E$6,C28) -> 0
B29: =B28+1 -> 8 | E29: =IF(D29<$E$6,C29) -> 0
B30: =B29+1 -> 9 | E30: =IF(D30<$E$6,C30) -> 0
B31: =B30+1 -> 10 | E31: =IF(D31<$E$6,C31) -> 0
A32: x | B32: Total | E32: =SUM(E21:E31) -> 7.4212
